cmoncrawl_fetcher.py
cmoncrawl_fetcher-0.1.0.dist-info/LICENSE
cmoncrawl_fetcher-0.1.0.dist-info/METADATA
cmoncrawl_fetcher-0.1.0.dist-info/WHEEL
cmoncrawl_fetcher-0.1.0.dist-info/RECORD
