Metadata-Version: 2.1
Name: cmoncrawl-fetcher
Version: 0.1.0
Summary: Fetches files of desired type from common crawler's database
License: GPLv3
Author: Kris Udomwongsa
Author-email: krisudomwongsa@gmail.com
Requires-Python: >=3.10,<4.0
Classifier: License :: Other/Proprietary License
Classifier: Programming Language :: Python :: 3
Classifier: Programming Language :: Python :: 3.10
Classifier: Programming Language :: Python :: 3.11
Requires-Dist: requests (>=2.31.0,<3.0.0)
Project-URL: repository, https://github.com/bread-b4nk/CmonCrawl-Fetcher
